ddwrt_conn_tracker/README.md
ddwrt_conn_tracker/__init__.py
ddwrt_conn_tracker/definitions.py
ddwrt_conn_tracker/tracker.py
ddwrt_conn_tracker/ddwrt/__init__.py
ddwrt_conn_tracker/ddwrt/routerssh.py
ddwrt_conn_tracker/models/__init__.py
ddwrt_conn_tracker/models/constants.py
ddwrt_conn_tracker/models/first_run.py
ddwrt_conn_tracker/models/main.py
ddwrt_conn_tracker/utils/__init__.py
ddwrt_conn_tracker/utils/cmd_args.py
DDWRT_Tracker-0.0.1.dev34.dist-info/AUTHORS
DDWRT_Tracker-0.0.1.dev34.dist-info/METADATA
DDWRT_Tracker-0.0.1.dev34.dist-info/WHEEL
DDWRT_Tracker-0.0.1.dev34.dist-info/pbr.json
DDWRT_Tracker-0.0.1.dev34.dist-info/top_level.txt
DDWRT_Tracker-0.0.1.dev34.dist-info/RECORD
