Metadata-Version: 2.1
Name: DDWRT-Tracker
Version: 0.0.1.dev34
Summary: Connection tracker for DD-WRT routers
Home-page: https://github.com/licht1stein/ddwrt-connection-tracker
Author: licht1stein, dana1313, lerzn
Author-email: UNKNOWN
License: UNKNOWN
Platform: UNKNOWN
Requires-Dist: ansimarkup (==1.4.0)
Requires-Dist: asn1crypto (==0.24.0)
Requires-Dist: attrs (==19.1.0)
Requires-Dist: bcrypt (==3.1.6)
Requires-Dist: better-exceptions-fork (==0.2.1.post6)
Requires-Dist: certifi (==2019.3.9)
Requires-Dist: cffi (==1.12.3)
Requires-Dist: colorama (==0.4.1)
Requires-Dist: cryptography (==2.6.1)
Requires-Dist: fabric (==2.4.0)
Requires-Dist: invoke (==1.2.0)
Requires-Dist: loguru (==0.2.5)
Requires-Dist: paramiko (==2.4.2)
Requires-Dist: pyasn1 (==0.4.5)
Requires-Dist: pycparser (==2.19)
Requires-Dist: Pygments (==2.4.0)
Requires-Dist: PyNaCl (==1.3.0)
Requires-Dist: six (==1.12.0)
Requires-Dist: SQLAlchemy (==1.3.3)
Requires-Dist: virtualenv (==16.6.0)
Requires-Dist: virtualenv-clone (==0.5.3)
